{
  "bag_stem": "ch_chicken_4",
  "source": "optical_flow_gui",
  "frames": {
    "000000": {
      "needle_tip": [
        658,
        522
      ],
      "needle_tail": [
        677,
        414
      ],
      "status": "ok",
      "method": "mask_skeleton_endpoints",
      "occluded": {
        "tip": true,
        "tail": false
      }
    },
    "000001": {
      "needle_tip": [
        660,
        524
      ],
      "needle_tail": [
        686,
        419
      ],
      "status": "ok",
      "method": "mask_skeleton_endpoints",
      "occluded": {
        "tip": true,
        "tail": false
      }
    },
    "000002": {
      "needle_tip": [
        654,
        521
      ],
      "needle_tail": [
        687,
        416
      ],
      "occluded": {
        "tip": true,
        "tail": false
      },
      "status": "ok",
      "method": "optical_flow_gui"
    },
    "000003": {
      "needle_tip": [
        511,
        516
      ],
      "needle_tail": [
        681,
        416
      ],
      "occluded": {
        "tip": false,
        "tail": false
      },
      "status": "ok",
      "method": "optical_flow_gui"
    },
    "000004": {
      "needle_tip": [
        479,
        484
      ],
      "needle_tail": [
        673,
        420
      ],
      "occluded": {
        "tip": false,
        "tail": false
      },
      "status": "ok",
      "method": "optical_flow_gui"
    },
    "000005": {
      "needle_tip": [
        452,
        458
      ],
      "needle_tail": [
        659,
        425
      ],
      "occluded": {
        "tip": false,
        "tail": false
      },
      "status": "ok",
      "method": "optical_flow_gui"
    },
    "000006": {
      "needle_tip": [
        449,
        451
      ],
      "needle_tail": [
        648,
        426
      ],
      "occluded": {
        "tip": false,
        "tail": false
      },
      "status": "ok",
      "method": "optical_flow_gui"
    },
    "000007": {
      "needle_tip": [
        446,
        457
      ],
      "needle_tail": [
        646,
        425
      ],
      "occluded": {
        "tip": false,
        "tail": false
      },
      "status": "ok",
      "method": "optical_flow_gui"
    },
    "000008": {
      "needle_tip": [
        448,
        460
      ],
      "needle_tail": [
        644,
        426
      ],
      "occluded": {
        "tip": false,
        "tail": false
      },
      "status": "ok",
      "method": "optical_flow_gui"
    },
    "000009": {
      "needle_tip": [
        439,
        463
      ],
      "needle_tail": [
        636,
        428
      ],
      "occluded": {
        "tip": false,
        "tail": false
      },
      "status": "ok",
      "method": "optical_flow_gui"
    },
    "000010": {
      "needle_tip": [
        428,
        468
      ],
      "needle_tail": [
        626,
        431
      ],
      "occluded": {
        "tip": false,
        "tail": false
      },
      "status": "ok",
      "method": "optical_flow_gui"
    },
    "000011": {
      "needle_tip": [
        419,
        470
      ],
      "needle_tail": [
        618,
        435
      ],
      "occluded": {
        "tip": false,
        "tail": false
      },
      "status": "ok",
      "method": "optical_flow_gui"
    },
    "000012": {
      "needle_tip": [
        414,
        475
      ],
      "needle_tail": [
        615,
        439
      ],
      "occluded": {
        "tip": false,
        "tail": false
      },
      "status": "ok",
      "method": "optical_flow_gui"
    },
    "000013": {
      "needle_tip": [
        412,
        476
      ],
      "needle_tail": [
        615,
        440
      ],
      "occluded": {
        "tip": false,
        "tail": false
      },
      "status": "ok",
      "method": "optical_flow_gui"
    },
    "000014": {
      "needle_tip": [
        414,
        479
      ],
      "needle_tail": [
        615,
        441
      ],
      "occluded": {
        "tip": false,
        "tail": false
      },
      "status": "ok",
      "method": "optical_flow_gui"
    },
    "000015": {
      "needle_tip": [
        416,
        484
      ],
      "needle_tail": [
        614,
        443
      ],
      "occluded": {
        "tip": false,
        "tail": false
      },
      "status": "ok",
      "method": "optical_flow_gui"
    },
    "000016": {
      "needle_tip": [
        416,
        478
      ],
      "needle_tail": [
        616,
        449
      ],
      "occluded": {
        "tip": false,
        "tail": false
      },
      "status": "ok",
      "method": "optical_flow_gui"
    },
    "000017": {
      "needle_tip": [
        418,
        479
      ],
      "needle_tail": [
        620,
        455
      ],
      "occluded": {
        "tip": false,
        "tail": false
      },
      "status": "ok",
      "method": "optical_flow_gui"
    },
    "000018": {
      "needle_tip": [
        417,
        479
      ],
      "needle_tail": [
        622,
        459
      ],
      "occluded": {
        "tip": false,
        "tail": false
      },
      "status": "ok",
      "method": "optical_flow_gui"
    },
    "000019": {
      "needle_tip": [
        417,
        484
      ],
      "needle_tail": [
        624,
        463
      ],
      "occluded": {
        "tip": false,
        "tail": false
      },
      "status": "ok",
      "method": "optical_flow_gui"
    },
    "000020": {
      "needle_tip": [
        417,
        489
      ],
      "needle_tail": [
        627,
        465
      ],
      "occluded": {
        "tip": false,
        "tail": false
      },
      "status": "ok",
      "method": "optical_flow_gui"
    },
    "000021": {
      "needle_tip": [
        417,
        497
      ],
      "needle_tail": [
        634,
        469
      ],
      "occluded": {
        "tip": false,
        "tail": false
      },
      "status": "ok",
      "method": "optical_flow_gui"
    },
    "000022": {
      "needle_tip": [
        420,
        502
      ],
      "needle_tail": [
        644,
        473
      ],
      "occluded": {
        "tip": false,
        "tail": false
      },
      "status": "ok",
      "method": "optical_flow_gui"
    },
    "000023": {
      "needle_tip": [
        448,
        523
      ],
      "needle_tail": [
        657,
        472
      ],
      "occluded": {
        "tip": false,
        "tail": false
      },
      "status": "ok",
      "method": "optical_flow_gui"
    },
    "000024": {
      "needle_tip": [
        449,
        526
      ],
      "needle_tail": [
        669,
        469
      ],
      "occluded": {
        "tip": false,
        "tail": false
      },
      "status": "ok",
      "method": "optical_flow_gui"
    },
    "000025": {
      "needle_tip": [
        500,
        555
      ],
      "needle_tail": [
        695,
        467
      ],
      "occluded": {
        "tip": false,
        "tail": false
      },
      "status": "ok",
      "method": "optical_flow_gui"
    },
    "000026": {
      "needle_tip": [
        542,
        555
      ],
      "needle_tail": [
        730,
        453
      ],
      "occluded": {
        "tip": false,
        "tail": false
      },
      "status": "ok",
      "method": "optical_flow_gui"
    },
    "000027": {
      "needle_tip": [
        561,
        533
      ],
      "needle_tail": [
        750,
        430
      ],
      "occluded": {
        "tip": false,
        "tail": false
      },
      "status": "ok",
      "method": "optical_flow_gui"
    },
    "000028": {
      "needle_tip": [
        569,
        529
      ],
      "needle_tail": [
        754,
        421
      ],
      "occluded": {
        "tip": false,
        "tail": false
      },
      "status": "ok",
      "method": "optical_flow_gui"
    },
    "000029": {
      "needle_tip": [
        577,
        522
      ],
      "needle_tail": [
        760,
        409
      ],
      "occluded": {
        "tip": false,
        "tail": false
      },
      "status": "ok",
      "method": "optical_flow_gui"
    },
    "000030": {
      "needle_tip": [
        585,
        514
      ],
      "needle_tail": [
        766,
        394
      ],
      "occluded": {
        "tip": false,
        "tail": false
      },
      "status": "ok",
      "method": "optical_flow_gui"
    },
    "000031": {
      "needle_tip": [
        584,
        512
      ],
      "needle_tail": [
        766,
        392
      ],
      "occluded": {
        "tip": false,
        "tail": false
      },
      "status": "ok",
      "method": "optical_flow_gui"
    },
    "000032": {
      "needle_tip": [
        587,
        508
      ],
      "needle_tail": [
        769,
        392
      ],
      "occluded": {
        "tip": false,
        "tail": false
      },
      "status": "ok",
      "method": "optical_flow_gui"
    },
    "000033": {
      "needle_tip": [
        589,
        507
      ],
      "needle_tail": [
        770,
        392
      ],
      "occluded": {
        "tip": false,
        "tail": false
      },
      "status": "ok",
      "method": "optical_flow_gui"
    },
    "000034": {
      "needle_tip": [
        585,
        509
      ],
      "needle_tail": [
        771,
        392
      ],
      "occluded": {
        "tip": false,
        "tail": false
      },
      "status": "ok",
      "method": "optical_flow_gui"
    },
    "000035": {
      "needle_tip": [
        619,
        517
      ],
      "needle_tail": [
        784,
        375
      ],
      "occluded": {
        "tip": false,
        "tail": false
      },
      "status": "ok",
      "method": "optical_flow_gui"
    },
    "000036": {
      "needle_tip": [
        636,
        505
      ],
      "needle_tail": [
        810,
        364
      ],
      "occluded": {
        "tip": false,
        "tail": false
      },
      "status": "ok",
      "method": "optical_flow_gui"
    },
    "000037": {
      "needle_tip": [
        647,
        503
      ],
      "needle_tail": [
        824,
        358
      ],
      "occluded": {
        "tip": false,
        "tail": false
      },
      "status": "ok",
      "method": "optical_flow_gui"
    },
    "000038": {
      "needle_tip": [
        655,
        499
      ],
      "needle_tail": [
        834,
        354
      ],
      "occluded": {
        "tip": false,
        "tail": false
      },
      "status": "ok",
      "method": "optical_flow_gui"
    },
    "000039": {
      "needle_tip": [
        658,
        500
      ],
      "needle_tail": [
        841,
        353
      ],
      "occluded": {
        "tip": false,
        "tail": false
      },
      "status": "ok",
      "method": "optical_flow_gui"
    },
    "000040": {
      "needle_tip": [
        662,
        506
      ],
      "needle_tail": [
        846,
        352
      ],
      "occluded": {
        "tip": false,
        "tail": false
      },
      "status": "ok",
      "method": "optical_flow_gui"
    },
    "000041": {
      "needle_tip": [
        665,
        511
      ],
      "needle_tail": [
        851,
        353
      ],
      "occluded": {
        "tip": false,
        "tail": false
      },
      "status": "ok",
      "method": "optical_flow_gui"
    },
    "000042": {
      "needle_tip": [
        664,
        515
      ],
      "needle_tail": [
        853,
        354
      ],
      "occluded": {
        "tip": false,
        "tail": false
      },
      "status": "ok",
      "method": "optical_flow_gui"
    },
    "000043": {
      "needle_tip": [
        660,
        522
      ],
      "needle_tail": [
        856,
        357
      ],
      "occluded": {
        "tip": false,
        "tail": false
      },
      "status": "ok",
      "method": "optical_flow_gui"
    },
    "000044": {
      "needle_tip": [
        661,
        529
      ],
      "needle_tail": [
        859,
        360
      ],
      "occluded": {
        "tip": false,
        "tail": false
      },
      "status": "ok",
      "method": "optical_flow_gui"
    },
    "000045": {
      "needle_tip": [
        655,
        529
      ],
      "needle_tail": [
        860,
        362
      ],
      "occluded": {
        "tip": false,
        "tail": false
      },
      "status": "ok",
      "method": "optical_flow_gui"
    },
    "000046": {
      "needle_tip": [
        650,
        531
      ],
      "needle_tail": [
        863,
        376
      ],
      "occluded": {
        "tip": false,
        "tail": false
      },
      "status": "ok",
      "method": "optical_flow_gui"
    },
    "000047": {
      "needle_tip": [
        637,
        537
      ],
      "needle_tail": [
        862,
        395
      ],
      "occluded": {
        "tip": false,
        "tail": false
      },
      "status": "ok",
      "method": "optical_flow_gui"
    },
    "000048": {
      "needle_tip": [
        615,
        542
      ],
      "needle_tail": [
        854,
        421
      ],
      "occluded": {
        "tip": false,
        "tail": false
      },
      "status": "ok",
      "method": "optical_flow_gui"
    },
    "000049": {
      "needle_tip": [
        625,
        540
      ],
      "needle_tail": [
        848,
        434
      ],
      "occluded": {
        "tip": true,
        "tail": false
      },
      "status": "ok",
      "method": "optical_flow_gui"
    },
    "000050": {
      "needle_tip": [
        622,
        541
      ],
      "needle_tail": [
        848,
        435
      ],
      "occluded": {
        "tip": true,
        "tail": false
      },
      "status": "ok",
      "method": "optical_flow_gui"
    },
    "000051": {
      "needle_tip": [
        618,
        542
      ],
      "needle_tail": [
        838,
        454
      ],
      "occluded": {
        "tip": true,
        "tail": false
      },
      "status": "ok",
      "method": "optical_flow_gui"
    },
    "000052": {
      "needle_tip": [
        595,
        545
      ],
      "needle_tail": [
        808,
        478
      ],
      "occluded": {
        "tip": true,
        "tail": false
      },
      "status": "ok",
      "method": "optical_flow_gui"
    },
    "000053": {
      "needle_tip": [
        572,
        552
      ],
      "needle_tail": [
        801,
        485
      ],
      "occluded": {
        "tip": true,
        "tail": false
      },
      "status": "ok",
      "method": "optical_flow_gui"
    },
    "000054": {
      "needle_tip": [
        554,
        571
      ],
      "needle_tail": [
        796,
        494
      ],
      "occluded": {
        "tip": true,
        "tail": false
      },
      "status": "ok",
      "method": "optical_flow_gui"
    },
    "000055": {
      "needle_tip": [
        553,
        570
      ],
      "needle_tail": [
        794,
        497
      ],
      "occluded": {
        "tip": true,
        "tail": false
      },
      "status": "ok",
      "method": "optical_flow_gui"
    },
    "000056": {
      "needle_tip": [
        551,
        573
      ],
      "needle_tail": [
        792,
        501
      ],
      "occluded": {
        "tip": true,
        "tail": false
      },
      "status": "ok",
      "method": "optical_flow_gui"
    },
    "000057": {
      "needle_tip": [
        546,
        577
      ],
      "needle_tail": [
        792,
        505
      ],
      "occluded": {
        "tip": true,
        "tail": false
      },
      "status": "ok",
      "method": "optical_flow_gui"
    },
    "000058": {
      "needle_tip": [
        545,
        583
      ],
      "needle_tail": [
        793,
        508
      ],
      "occluded": {
        "tip": true,
        "tail": false
      },
      "status": "ok",
      "method": "optical_flow_gui"
    },
    "000059": {
      "needle_tip": [
        544,
        584
      ],
      "needle_tail": [
        793,
        510
      ],
      "occluded": {
        "tip": true,
        "tail": false
      },
      "status": "ok",
      "method": "optical_flow_gui"
    },
    "000060": {
      "needle_tip": [
        544,
        586
      ],
      "needle_tail": [
        794,
        512
      ],
      "occluded": {
        "tip": true,
        "tail": false
      },
      "status": "ok",
      "method": "optical_flow_gui"
    },
    "000061": {
      "needle_tip": [
        544,
        589
      ],
      "needle_tail": [
        794,
        513
      ],
      "occluded": {
        "tip": true,
        "tail": false
      },
      "status": "ok",
      "method": "optical_flow_gui"
    },
    "000062": {
      "needle_tip": [
        545,
        592
      ],
      "needle_tail": [
        795,
        514
      ],
      "occluded": {
        "tip": true,
        "tail": false
      },
      "status": "ok",
      "method": "optical_flow_gui"
    },
    "000063": {
      "needle_tip": [
        547,
        596
      ],
      "needle_tail": [
        795,
        516
      ],
      "occluded": {
        "tip": true,
        "tail": false
      },
      "status": "ok",
      "method": "optical_flow_gui"
    },
    "000064": {
      "needle_tip": [
        547,
        601
      ],
      "needle_tail": [
        797,
        520
      ],
      "occluded": {
        "tip": true,
        "tail": false
      },
      "status": "ok",
      "method": "optical_flow_gui"
    },
    "000065": {
      "needle_tip": [
        546,
        601
      ],
      "needle_tail": [
        798,
        523
      ],
      "occluded": {
        "tip": true,
        "tail": false
      },
      "status": "ok",
      "method": "optical_flow_gui"
    },
    "000066": {
      "needle_tip": [
        547,
        603
      ],
      "needle_tail": [
        800,
        525
      ],
      "occluded": {
        "tip": true,
        "tail": false
      },
      "status": "ok",
      "method": "optical_flow_gui"
    },
    "000067": {
      "needle_tip": [
        545,
        604
      ],
      "needle_tail": [
        800,
        526
      ],
      "occluded": {
        "tip": true,
        "tail": false
      },
      "status": "ok",
      "method": "optical_flow_gui"
    },
    "000068": {
      "needle_tip": [
        545,
        602
      ],
      "needle_tail": [
        800,
        526
      ],
      "occluded": {
        "tip": true,
        "tail": false
      },
      "status": "ok",
      "method": "optical_flow_gui"
    },
    "000069": {
      "needle_tip": [
        543,
        601
      ],
      "needle_tail": [
        800,
        526
      ],
      "occluded": {
        "tip": true,
        "tail": false
      },
      "status": "ok",
      "method": "optical_flow_gui"
    },
    "000070": {
      "needle_tip": [
        545,
        603
      ],
      "needle_tail": [
        802,
        525
      ],
      "occluded": {
        "tip": true,
        "tail": false
      },
      "status": "ok",
      "method": "optical_flow_gui"
    },
    "000071": {
      "needle_tip": [
        395,
        642
      ],
      "needle_tail": [
        809,
        518
      ],
      "occluded": {
        "tip": true,
        "tail": false
      },
      "status": "ok",
      "method": "optical_flow_gui"
    },
    "000072": {
      "needle_tip": [
        307,
        576
      ],
      "needle_tail": [
        826,
        499
      ],
      "occluded": {
        "tip": true,
        "tail": false
      },
      "status": "ok",
      "method": "optical_flow_gui"
    },
    "000073": {
      "needle_tip": [
        342,
        597
      ],
      "needle_tail": [
        840,
        467
      ],
      "occluded": {
        "tip": true,
        "tail": false
      },
      "status": "ok",
      "method": "optical_flow_gui"
    },
    "000074": {
      "needle_tip": [
        346,
        596
      ],
      "needle_tail": [
        846,
        448
      ],
      "occluded": {
        "tip": true,
        "tail": false
      },
      "status": "ok",
      "method": "optical_flow_gui"
    },
    "000075": {
      "needle_tip": [
        346,
        589
      ],
      "needle_tail": [
        850,
        437
      ],
      "occluded": {
        "tip": true,
        "tail": false
      },
      "status": "ok",
      "method": "optical_flow_gui"
    },
    "000076": {
      "needle_tip": [
        349,
        589
      ],
      "needle_tail": [
        851,
        434
      ],
      "occluded": {
        "tip": true,
        "tail": false
      },
      "status": "ok",
      "method": "optical_flow_gui"
    },
    "000077": {
      "needle_tip": [
        349,
        590
      ],
      "needle_tail": [
        852,
        434
      ],
      "occluded": {
        "tip": true,
        "tail": false
      },
      "status": "ok",
      "method": "optical_flow_gui"
    },
    "000078": {
      "needle_tip": [
        348,
        589
      ],
      "needle_tail": [
        852,
        433
      ],
      "occluded": {
        "tip": true,
        "tail": false
      },
      "status": "ok",
      "method": "optical_flow_gui"
    },
    "000079": {
      "needle_tip": [
        354,
        593
      ],
      "needle_tail": [
        853,
        431
      ],
      "occluded": {
        "tip": true,
        "tail": false
      },
      "status": "ok",
      "method": "optical_flow_gui"
    },
    "000080": {
      "needle_tip": [
        354,
        584
      ],
      "needle_tail": [
        866,
        430
      ],
      "occluded": {
        "tip": true,
        "tail": false
      },
      "status": "ok",
      "method": "optical_flow_gui"
    },
    "000081": {
      "needle_tip": [
        332,
        555
      ],
      "needle_tail": [
        870,
        431
      ],
      "occluded": {
        "tip": true,
        "tail": false
      },
      "status": "ok",
      "method": "optical_flow_gui"
    },
    "000082": {
      "needle_tip": [
        314,
        529
      ],
      "needle_tail": [
        869,
        439
      ],
      "occluded": {
        "tip": true,
        "tail": false
      },
      "status": "ok",
      "method": "optical_flow_gui"
    },
    "000083": {
      "needle_tip": [
        310,
        527
      ],
      "needle_tail": [
        869,
        441
      ],
      "occluded": {
        "tip": true,
        "tail": false
      },
      "status": "ok",
      "method": "optical_flow_gui"
    },
    "000084": {
      "needle_tip": [
        310,
        526
      ],
      "needle_tail": [
        869,
        441
      ],
      "occluded": {
        "tip": true,
        "tail": false
      },
      "status": "ok",
      "method": "optical_flow_gui"
    },
    "000085": {
      "needle_tip": [
        310,
        526
      ],
      "needle_tail": [
        869,
        441
      ],
      "occluded": {
        "tip": true,
        "tail": false
      },
      "status": "ok",
      "method": "optical_flow_gui"
    },
    "000086": {
      "needle_tip": [
        294,
        500
      ],
      "needle_tail": [
        865,
        453
      ],
      "occluded": {
        "tip": true,
        "tail": false
      },
      "status": "ok",
      "method": "optical_flow_gui"
    },
    "000087": {
      "needle_tip": [
        317,
        530
      ],
      "needle_tail": [
        861,
        465
      ],
      "occluded": {
        "tip": true,
        "tail": false
      },
      "status": "ok",
      "method": "optical_flow_gui"
    },
    "000088": {
      "needle_tip": [
        317,
        531
      ],
      "needle_tail": [
        861,
        465
      ],
      "occluded": {
        "tip": true,
        "tail": false
      },
      "status": "ok",
      "method": "optical_flow_gui"
    },
    "000089": {
      "needle_tip": [
        417,
        563
      ],
      "needle_tail": [
        855,
        475
      ],
      "occluded": {
        "tip": true,
        "tail": false
      },
      "status": "ok",
      "method": "optical_flow_gui"
    },
    "000090": {
      "needle_tip": [
        423,
        558
      ],
      "needle_tail": [
        845,
        491
      ],
      "occluded": {
        "tip": true,
        "tail": false
      },
      "status": "ok",
      "method": "optical_flow_gui"
    },
    "000091": {
      "needle_tip": [
        420,
        561
      ],
      "needle_tail": [
        837,
        501
      ],
      "occluded": {
        "tip": true,
        "tail": false
      },
      "status": "ok",
      "method": "optical_flow_gui"
    },
    "000092": {
      "needle_tip": [
        405,
        565
      ],
      "needle_tail": [
        824,
        514
      ],
      "occluded": {
        "tip": true,
        "tail": false
      },
      "status": "ok",
      "method": "optical_flow_gui"
    },
    "000093": {
      "needle_tip": [
        394,
        589
      ],
      "needle_tail": [
        813,
        521
      ],
      "occluded": {
        "tip": true,
        "tail": false
      },
      "status": "ok",
      "method": "optical_flow_gui"
    },
    "000094": {
      "needle_tip": [
        392,
        597
      ],
      "needle_tail": [
        812,
        522
      ],
      "occluded": {
        "tip": true,
        "tail": false
      },
      "status": "ok",
      "method": "optical_flow_gui"
    },
    "000095": {
      "needle_tip": [
        394,
        599
      ],
      "needle_tail": [
        812,
        522
      ],
      "occluded": {
        "tip": true,
        "tail": false
      },
      "status": "ok",
      "method": "optical_flow_gui"
    },
    "000096": {
      "needle_tip": [
        390,
        618
      ],
      "needle_tail": [
        809,
        519
      ],
      "occluded": {
        "tip": true,
        "tail": false
      },
      "status": "ok",
      "method": "optical_flow_gui"
    },
    "000097": {
      "needle_tip": [
        320,
        662
      ],
      "needle_tail": [
        791,
        514
      ],
      "occluded": {
        "tip": true,
        "tail": false
      },
      "status": "ok",
      "method": "optical_flow_gui"
    },
    "000098": {
      "needle_tip": [
        324,
        659
      ],
      "needle_tail": [
        784,
        511
      ],
      "occluded": {
        "tip": true,
        "tail": false
      },
      "status": "ok",
      "method": "optical_flow_gui"
    },
    "000099": {
      "needle_tip": [
        265,
        659
      ],
      "needle_tail": [
        728,
        527
      ],
      "occluded": {
        "tip": true,
        "tail": false
      },
      "status": "ok",
      "method": "optical_flow_gui"
    },
    "000100": {
      "needle_tip": [
        523,
        623
      ],
      "needle_tail": [
        684,
        528
      ],
      "occluded": {
        "tip": true,
        "tail": false
      },
      "status": "ok",
      "method": "optical_flow_gui"
    },
    "000101": {
      "needle_tip": [
        524,
        622
      ],
      "needle_tail": [
        671,
        530
      ],
      "occluded": {
        "tip": true,
        "tail": false
      },
      "status": "ok",
      "method": "optical_flow_gui"
    },
    "000102": {
      "needle_tip": [
        525,
        624
      ],
      "needle_tail": [
        663,
        530
      ],
      "occluded": {
        "tip": true,
        "tail": false
      },
      "status": "ok",
      "method": "optical_flow_gui"
    },
    "000103": {
      "needle_tip": [
        525,
        628
      ],
      "needle_tail": [
        644,
        527
      ],
      "occluded": {
        "tip": true,
        "tail": false
      },
      "status": "ok",
      "method": "optical_flow_gui"
    },
    "000104": {
      "needle_tip": [
        524,
        631
      ],
      "needle_tail": [
        627,
        526
      ],
      "occluded": {
        "tip": true,
        "tail": false
      },
      "status": "ok",
      "method": "optical_flow_gui"
    },
    "000105": {
      "needle_tip": [
        522,
        632
      ],
      "needle_tail": [
        617,
        526
      ],
      "occluded": {
        "tip": true,
        "tail": false
      },
      "status": "ok",
      "method": "optical_flow_gui"
    },
    "000106": {
      "needle_tip": [
        519,
        632
      ],
      "needle_tail": [
        613,
        527
      ],
      "occluded": {
        "tip": true,
        "tail": false
      },
      "status": "ok",
      "method": "optical_flow_gui"
    },
    "000107": {
      "needle_tip": [
        519,
        630
      ],
      "needle_tail": [
        613,
        527
      ],
      "occluded": {
        "tip": true,
        "tail": false
      },
      "status": "ok",
      "method": "optical_flow_gui"
    },
    "000108": {
      "needle_tip": [
        520,
        631
      ],
      "needle_tail": [
        613,
        527
      ],
      "occluded": {
        "tip": true,
        "tail": false
      },
      "status": "ok",
      "method": "optical_flow_gui"
    },
    "000109": {
      "needle_tip": [
        522,
        631
      ],
      "needle_tail": [
        613,
        528
      ],
      "occluded": {
        "tip": true,
        "tail": false
      },
      "status": "ok",
      "method": "optical_flow_gui"
    },
    "000110": {
      "needle_tip": [
        525,
        632
      ],
      "needle_tail": [
        614,
        528
      ],
      "occluded": {
        "tip": true,
        "tail": false
      },
      "status": "ok",
      "method": "optical_flow_gui"
    },
    "000111": {
      "needle_tip": [
        532,
        634
      ],
      "needle_tail": [
        622,
        531
      ],
      "occluded": {
        "tip": true,
        "tail": false
      },
      "status": "ok",
      "method": "optical_flow_gui"
    },
    "000112": {
      "needle_tip": [
        547,
        631
      ],
      "needle_tail": [
        654,
        536
      ],
      "occluded": {
        "tip": true,
        "tail": false
      },
      "status": "ok",
      "method": "optical_flow_gui"
    },
    "000113": {
      "needle_tip": [
        559,
        628
      ],
      "needle_tail": [
        681,
        535
      ],
      "occluded": {
        "tip": true,
        "tail": false
      },
      "status": "ok",
      "method": "optical_flow_gui"
    },
    "000114": {
      "needle_tip": [
        572,
        628
      ],
      "needle_tail": [
        703,
        527
      ],
      "occluded": {
        "tip": true,
        "tail": false
      },
      "status": "ok",
      "method": "optical_flow_gui"
    },
    "000115": {
      "needle_tip": [
        585,
        630
      ],
      "needle_tail": [
        724,
        516
      ],
      "occluded": {
        "tip": true,
        "tail": false
      },
      "status": "ok",
      "method": "optical_flow_gui"
    },
    "000116": {
      "needle_tip": [
        608,
        634
      ],
      "needle_tail": [
        744,
        502
      ],
      "occluded": {
        "tip": true,
        "tail": false
      },
      "status": "ok",
      "method": "optical_flow_gui"
    },
    "000117": {
      "needle_tip": [
        636,
        634
      ],
      "needle_tail": [
        760,
        491
      ],
      "occluded": {
        "tip": true,
        "tail": false
      },
      "status": "ok",
      "method": "optical_flow_gui"
    },
    "000118": {
      "needle_tip": [
        659,
        631
      ],
      "needle_tail": [
        773,
        479
      ],
      "occluded": {
        "tip": true,
        "tail": false
      },
      "status": "ok",
      "method": "optical_flow_gui"
    },
    "000119": {
      "needle_tip": [
        692,
        620
      ],
      "needle_tail": [
        794,
        456
      ],
      "occluded": {
        "tip": true,
        "tail": false
      },
      "status": "ok",
      "method": "optical_flow_gui"
    },
    "000120": {
      "needle_tip": [
        704,
        615
      ],
      "needle_tail": [
        801,
        448
      ],
      "occluded": {
        "tip": true,
        "tail": false
      },
      "status": "ok",
      "method": "optical_flow_gui"
    },
    "000121": {
      "needle_tip": [
        717,
        607
      ],
      "needle_tail": [
        813,
        440
      ],
      "occluded": {
        "tip": true,
        "tail": false
      },
      "status": "ok",
      "method": "optical_flow_gui"
    },
    "000122": {
      "needle_tip": [
        719,
        598
      ],
      "needle_tail": [
        822,
        430
      ],
      "occluded": {
        "tip": true,
        "tail": false
      },
      "status": "ok",
      "method": "optical_flow_gui"
    },
    "000123": {
      "needle_tip": [
        723,
        589
      ],
      "needle_tail": [
        832,
        415
      ],
      "occluded": {
        "tip": true,
        "tail": false
      },
      "status": "ok",
      "method": "optical_flow_gui"
    },
    "000124": {
      "needle_tip": [
        722,
        583
      ],
      "needle_tail": [
        841,
        390
      ],
      "occluded": {
        "tip": true,
        "tail": false
      },
      "status": "ok",
      "method": "optical_flow_gui"
    },
    "000125": {
      "needle_tip": [
        725,
        579
      ],
      "needle_tail": [
        847,
        370
      ],
      "occluded": {
        "tip": true,
        "tail": false
      },
      "status": "ok",
      "method": "optical_flow_gui"
    },
    "000126": {
      "needle_tip": [
        782,
        600
      ],
      "needle_tail": [
        849,
        354
      ],
      "occluded": {
        "tip": false,
        "tail": false
      },
      "status": "ok",
      "method": "optical_flow_gui"
    },
    "000127": {
      "needle_tip": [
        796,
        587
      ],
      "needle_tail": [
        849,
        328
      ],
      "occluded": {
        "tip": false,
        "tail": false
      },
      "status": "ok",
      "method": "optical_flow_gui"
    },
    "000128": {
      "needle_tip": [
        809,
        557
      ],
      "needle_tail": [
        847,
        281
      ],
      "occluded": {
        "tip": false,
        "tail": false
      },
      "status": "ok",
      "method": "optical_flow_gui"
    },
    "000129": {
      "needle_tip": [
        818,
        542
      ],
      "needle_tail": [
        848,
        263
      ],
      "occluded": {
        "tip": false,
        "tail": false
      },
      "status": "ok",
      "method": "optical_flow_gui"
    },
    "000130": {
      "needle_tip": [
        808,
        529
      ],
      "needle_tail": [
        855,
        255
      ],
      "occluded": {
        "tip": false,
        "tail": false
      },
      "status": "ok",
      "method": "optical_flow_gui"
    },
    "000131": {
      "needle_tip": [
        785,
        507
      ],
      "needle_tail": [
        862,
        243
      ],
      "occluded": {
        "tip": false,
        "tail": false
      },
      "status": "ok",
      "method": "optical_flow_gui"
    },
    "000132": {
      "needle_tip": [
        776,
        505
      ],
      "needle_tail": [
        863,
        242
      ],
      "occluded": {
        "tip": false,
        "tail": false
      },
      "status": "ok",
      "method": "optical_flow_gui"
    },
    "000133": {
      "needle_tip": [
        774,
        506
      ],
      "needle_tail": [
        864,
        241
      ],
      "occluded": {
        "tip": false,
        "tail": false
      },
      "status": "ok",
      "method": "optical_flow_gui"
    },
    "000134": {
      "needle_tip": [
        779,
        504
      ],
      "needle_tail": [
        863,
        241
      ],
      "occluded": {
        "tip": false,
        "tail": false
      },
      "status": "ok",
      "method": "optical_flow_gui"
    },
    "000135": {
      "needle_tip": [
        779,
        504
      ],
      "needle_tail": [
        863,
        241
      ],
      "occluded": {
        "tip": false,
        "tail": false
      },
      "status": "ok",
      "method": "optical_flow_gui"
    },
    "000136": {
      "needle_tip": [
        775,
        504
      ],
      "needle_tail": [
        865,
        242
      ],
      "occluded": {
        "tip": false,
        "tail": false
      },
      "status": "ok",
      "method": "optical_flow_gui"
    },
    "000137": {
      "needle_tip": [
        776,
        506
      ],
      "needle_tail": [
        870,
        251
      ],
      "occluded": {
        "tip": false,
        "tail": false
      },
      "status": "ok",
      "method": "optical_flow_gui"
    },
    "000138": {
      "needle_tip": [
        769,
        509
      ],
      "needle_tail": [
        873,
        260
      ],
      "occluded": {
        "tip": false,
        "tail": false
      },
      "status": "ok",
      "method": "optical_flow_gui"
    },
    "000139": {
      "needle_tip": [
        737,
        516
      ],
      "needle_tail": [
        888,
        302
      ],
      "occluded": {
        "tip": false,
        "tail": false
      },
      "status": "ok",
      "method": "optical_flow_gui"
    },
    "000140": {
      "needle_tip": [
        726,
        519
      ],
      "needle_tail": [
        891,
        318
      ],
      "occluded": {
        "tip": false,
        "tail": false
      },
      "status": "ok",
      "method": "optical_flow_gui"
    },
    "000141": {
      "needle_tip": [
        716,
        521
      ],
      "needle_tail": [
        892,
        329
      ],
      "occluded": {
        "tip": false,
        "tail": false
      },
      "status": "ok",
      "method": "optical_flow_gui"
    },
    "000142": {
      "needle_tip": [
        718,
        522
      ],
      "needle_tail": [
        892,
        334
      ],
      "occluded": {
        "tip": false,
        "tail": false
      },
      "status": "ok",
      "method": "optical_flow_gui"
    },
    "000143": {
      "needle_tip": [
        718,
        522
      ],
      "needle_tail": [
        892,
        336
      ],
      "occluded": {
        "tip": false,
        "tail": false
      },
      "status": "ok",
      "method": "optical_flow_gui"
    },
    "000144": {
      "needle_tip": [
        730,
        520
      ],
      "needle_tail": [
        884,
        340
      ],
      "occluded": {
        "tip": true,
        "tail": false
      },
      "status": "ok",
      "method": "optical_flow_gui"
    },
    "000145": {
      "needle_tip": [
        779,
        530
      ],
      "needle_tail": [
        874,
        351
      ],
      "occluded": {
        "tip": true,
        "tail": false
      },
      "status": "ok",
      "method": "optical_flow_gui"
    },
    "000146": {
      "needle_tip": [
        791,
        534
      ],
      "needle_tail": [
        871,
        353
      ],
      "occluded": {
        "tip": true,
        "tail": false
      },
      "status": "ok",
      "method": "optical_flow_gui"
    },
    "000147": {
      "needle_tip": [
        797,
        531
      ],
      "needle_tail": [
        868,
        351
      ],
      "occluded": {
        "tip": true,
        "tail": false
      },
      "status": "ok",
      "method": "optical_flow_gui"
    },
    "000148": {
      "needle_tip": [
        798,
        530
      ],
      "needle_tail": [
        866,
        350
      ],
      "occluded": {
        "tip": true,
        "tail": false
      },
      "status": "ok",
      "method": "optical_flow_gui"
    },
    "000149": {
      "needle_tip": [
        798,
        525
      ],
      "needle_tail": [
        864,
        348
      ],
      "occluded": {
        "tip": true,
        "tail": false
      },
      "status": "ok",
      "method": "optical_flow_gui"
    },
    "000150": {
      "needle_tip": [
        799,
        526
      ],
      "needle_tail": [
        864,
        353
      ],
      "occluded": {
        "tip": true,
        "tail": false
      },
      "status": "ok",
      "method": "optical_flow_gui"
    },
    "000151": {
      "needle_tip": [
        800,
        533
      ],
      "needle_tail": [
        865,
        375
      ],
      "occluded": {
        "tip": true,
        "tail": false
      },
      "status": "ok",
      "method": "optical_flow_gui"
    },
    "000152": {
      "needle_tip": [
        802,
        535
      ],
      "needle_tail": [
        863,
        393
      ],
      "occluded": {
        "tip": true,
        "tail": false
      },
      "status": "ok",
      "method": "optical_flow_gui"
    },
    "000153": {
      "needle_tip": [
        802,
        540
      ],
      "needle_tail": [
        863,
        408
      ],
      "occluded": {
        "tip": true,
        "tail": false
      },
      "status": "ok",
      "method": "optical_flow_gui"
    },
    "000154": {
      "needle_tip": [
        796,
        540
      ],
      "needle_tail": [
        862,
        419
      ],
      "occluded": {
        "tip": true,
        "tail": false
      },
      "status": "ok",
      "method": "optical_flow_gui"
    },
    "000155": {
      "needle_tip": [
        796,
        537
      ],
      "needle_tail": [
        859,
        421
      ],
      "occluded": {
        "tip": true,
        "tail": false
      },
      "status": "ok",
      "method": "optical_flow_gui"
    },
    "000156": {
      "needle_tip": [
        794,
        540
      ],
      "needle_tail": [
        858,
        422
      ],
      "occluded": {
        "tip": true,
        "tail": false
      },
      "status": "ok",
      "method": "optical_flow_gui"
    },
    "000157": {
      "needle_tip": [
        791,
        541
      ],
      "needle_tail": [
        856,
        426
      ],
      "occluded": {
        "tip": true,
        "tail": false
      },
      "status": "ok",
      "method": "optical_flow_gui"
    },
    "000158": {
      "needle_tip": [
        779,
        547
      ],
      "needle_tail": [
        846,
        446
      ],
      "occluded": {
        "tip": true,
        "tail": false
      },
      "status": "ok",
      "method": "optical_flow_gui"
    },
    "000159": {
      "needle_tip": [
        824,
        545
      ],
      "needle_tail": [
        822,
        469
      ],
      "occluded": {
        "tip": true,
        "tail": false
      },
      "status": "ok",
      "method": "optical_flow_gui"
    },
    "000160": {
      "needle_tip": [
        808,
        555
      ],
      "needle_tail": [
        809,
        480
      ],
      "occluded": {
        "tip": true,
        "tail": false
      },
      "status": "ok",
      "method": "optical_flow_gui"
    },
    "000161": {
      "needle_tip": [
        791,
        564
      ],
      "needle_tail": [
        794,
        490
      ],
      "occluded": {
        "tip": true,
        "tail": false
      },
      "status": "ok",
      "method": "optical_flow_gui"
    },
    "000162": {
      "needle_tip": [
        778,
        570
      ],
      "needle_tail": [
        783,
        496
      ],
      "occluded": {
        "tip": true,
        "tail": false
      },
      "status": "ok",
      "method": "optical_flow_gui"
    },
    "000163": {
      "needle_tip": [
        765,
        575
      ],
      "needle_tail": [
        772,
        501
      ],
      "occluded": {
        "tip": true,
        "tail": false
      },
      "status": "ok",
      "method": "optical_flow_gui"
    },
    "000164": {
      "needle_tip": [
        752,
        578
      ],
      "needle_tail": [
        760,
        505
      ],
      "occluded": {
        "tip": true,
        "tail": false
      },
      "status": "ok",
      "method": "optical_flow_gui"
    },
    "000165": {
      "needle_tip": [
        745,
        580
      ],
      "needle_tail": [
        755,
        507
      ],
      "occluded": {
        "tip": true,
        "tail": false
      },
      "status": "ok",
      "method": "optical_flow_gui"
    },
    "000166": {
      "needle_tip": [
        740,
        581
      ],
      "needle_tail": [
        750,
        508
      ],
      "occluded": {
        "tip": true,
        "tail": false
      },
      "status": "ok",
      "method": "optical_flow_gui"
    },
    "000167": {
      "needle_tip": [
        739,
        582
      ],
      "needle_tail": [
        750,
        508
      ],
      "occluded": {
        "tip": true,
        "tail": false
      },
      "status": "ok",
      "method": "optical_flow_gui"
    },
    "000168": {
      "needle_tip": [
        739,
        582
      ],
      "needle_tail": [
        749,
        508
      ],
      "occluded": {
        "tip": true,
        "tail": false
      },
      "status": "ok",
      "method": "optical_flow_gui"
    },
    "000169": {
      "needle_tip": [
        739,
        579
      ],
      "needle_tail": [
        734,
        513
      ],
      "occluded": {
        "tip": true,
        "tail": false
      },
      "status": "ok",
      "method": "optical_flow_gui"
    },
    "000170": {
      "needle_tip": [
        737,
        570
      ],
      "needle_tail": [
        732,
        503
      ],
      "occluded": {
        "tip": true,
        "tail": false
      },
      "status": "ok",
      "method": "optical_flow_gui"
    },
    "000171": {
      "needle_tip": [
        738,
        568
      ],
      "needle_tail": [
        733,
        500
      ],
      "occluded": {
        "tip": true,
        "tail": false
      },
      "status": "ok",
      "method": "optical_flow_gui"
    },
    "000172": {
      "needle_tip": [
        737,
        567
      ],
      "needle_tail": [
        733,
        500
      ],
      "occluded": {
        "tip": true,
        "tail": false
      },
      "status": "ok",
      "method": "optical_flow_gui"
    },
    "000173": {
      "needle_tip": [
        737,
        567
      ],
      "needle_tail": [
        733,
        500
      ],
      "occluded": {
        "tip": true,
        "tail": false
      },
      "status": "ok",
      "method": "optical_flow_gui"
    },
    "000174": {
      "needle_tip": [
        734,
        567
      ],
      "needle_tail": [
        731,
        501
      ],
      "occluded": {
        "tip": true,
        "tail": false
      },
      "status": "ok",
      "method": "optical_flow_gui"
    },
    "000175": {
      "needle_tip": [
        730,
        569
      ],
      "needle_tail": [
        728,
        505
      ],
      "occluded": {
        "tip": true,
        "tail": false
      },
      "status": "ok",
      "method": "optical_flow_gui"
    },
    "000176": {
      "needle_tip": [
        729,
        571
      ],
      "needle_tail": [
        730,
        508
      ],
      "occluded": {
        "tip": true,
        "tail": false
      },
      "status": "ok",
      "method": "optical_flow_gui"
    },
    "000177": {
      "needle_tip": [
        728,
        570
      ],
      "needle_tail": [
        732,
        512
      ],
      "occluded": {
        "tip": true,
        "tail": false
      },
      "status": "ok",
      "method": "optical_flow_gui"
    },
    "000178": {
      "needle_tip": [
        539,
        438
      ],
      "needle_tail": [
        732,
        514
      ],
      "occluded": {
        "tip": false,
        "tail": false
      },
      "status": "ok",
      "method": "optical_flow_gui"
    },
    "000179": {
      "needle_tip": [
        553,
        421
      ],
      "needle_tail": [
        733,
        518
      ],
      "occluded": {
        "tip": false,
        "tail": false
      },
      "status": "ok",
      "method": "optical_flow_gui"
    },
    "000180": {
      "needle_tip": [
        560,
        413
      ],
      "needle_tail": [
        733,
        520
      ],
      "occluded": {
        "tip": false,
        "tail": false
      },
      "status": "ok",
      "method": "optical_flow_gui"
    },
    "000181": {
      "needle_tip": [
        565,
        407
      ],
      "needle_tail": [
        732,
        521
      ],
      "occluded": {
        "tip": false,
        "tail": false
      },
      "status": "ok",
      "method": "optical_flow_gui"
    },
    "000182": {
      "needle_tip": [
        566,
        399
      ],
      "needle_tail": [
        730,
        522
      ],
      "occluded": {
        "tip": false,
        "tail": false
      },
      "status": "ok",
      "method": "optical_flow_gui"
    },
    "000183": {
      "needle_tip": [
        566,
        393
      ],
      "needle_tail": [
        726,
        523
      ],
      "occluded": {
        "tip": false,
        "tail": false
      },
      "status": "ok",
      "method": "optical_flow_gui"
    },
    "000184": {
      "needle_tip": [
        565,
        394
      ],
      "needle_tail": [
        725,
        523
      ],
      "occluded": {
        "tip": false,
        "tail": false
      },
      "status": "ok",
      "method": "optical_flow_gui"
    },
    "000185": {
      "needle_tip": [
        565,
        391
      ],
      "needle_tail": [
        724,
        523
      ],
      "occluded": {
        "tip": false,
        "tail": false
      },
      "status": "ok",
      "method": "optical_flow_gui"
    },
    "000186": {
      "needle_tip": [
        565,
        391
      ],
      "needle_tail": [
        724,
        523
      ],
      "occluded": {
        "tip": false,
        "tail": false
      },
      "status": "ok",
      "method": "optical_flow_gui"
    },
    "000187": {
      "needle_tip": [
        564,
        392
      ],
      "needle_tail": [
        724,
        523
      ],
      "occluded": {
        "tip": false,
        "tail": false
      },
      "status": "ok",
      "method": "optical_flow_gui"
    },
    "000188": {
      "needle_tip": [
        564,
        390
      ],
      "needle_tail": [
        725,
        523
      ],
      "occluded": {
        "tip": false,
        "tail": false
      },
      "status": "ok",
      "method": "optical_flow_gui"
    },
    "000189": {
      "needle_tip": [
        564,
        394
      ],
      "needle_tail": [
        725,
        523
      ],
      "occluded": {
        "tip": false,
        "tail": false
      },
      "status": "ok",
      "method": "optical_flow_gui"
    },
    "000190": {
      "needle_tip": [
        563,
        394
      ],
      "needle_tail": [
        726,
        522
      ],
      "occluded": {
        "tip": false,
        "tail": false
      },
      "status": "ok",
      "method": "optical_flow_gui"
    },
    "000191": {
      "needle_tip": [
        562,
        396
      ],
      "needle_tail": [
        727,
        522
      ],
      "occluded": {
        "tip": false,
        "tail": false
      },
      "status": "ok",
      "method": "optical_flow_gui"
    },
    "000192": {
      "needle_tip": [
        562,
        399
      ],
      "needle_tail": [
        728,
        521
      ],
      "occluded": {
        "tip": false,
        "tail": false
      },
      "status": "ok",
      "method": "optical_flow_gui"
    },
    "000193": {
      "needle_tip": [
        560,
        405
      ],
      "needle_tail": [
        730,
        519
      ],
      "occluded": {
        "tip": false,
        "tail": false
      },
      "status": "ok",
      "method": "optical_flow_gui"
    },
    "000194": {
      "needle_tip": [
        559,
        405
      ],
      "needle_tail": [
        732,
        518
      ],
      "occluded": {
        "tip": false,
        "tail": false
      },
      "status": "ok",
      "method": "optical_flow_gui"
    },
    "000195": {
      "needle_tip": [
        553,
        417
      ],
      "needle_tail": [
        733,
        515
      ],
      "occluded": {
        "tip": false,
        "tail": false
      },
      "status": "ok",
      "method": "optical_flow_gui"
    },
    "000196": {
      "needle_tip": [
        526,
        502
      ],
      "needle_tail": [
        710,
        492
      ],
      "occluded": {
        "tip": false,
        "tail": false
      },
      "status": "ok",
      "method": "optical_flow_gui"
    },
    "000197": {
      "needle_tip": [
        509,
        504
      ],
      "needle_tail": [
        708,
        486
      ],
      "occluded": {
        "tip": false,
        "tail": false
      },
      "status": "ok",
      "method": "optical_flow_gui"
    },
    "000198": {
      "needle_tip": [
        511,
        503
      ],
      "needle_tail": [
        707,
        485
      ],
      "occluded": {
        "tip": false,
        "tail": false
      },
      "status": "ok",
      "method": "optical_flow_gui"
    },
    "000199": {
      "needle_tip": [
        520,
        516
      ],
      "needle_tail": [
        707,
        484
      ],
      "occluded": {
        "tip": true,
        "tail": false
      },
      "status": "ok",
      "method": "optical_flow_gui"
    },
    "000200": {
      "needle_tip": [
        528,
        504
      ],
      "needle_tail": [
        707,
        485
      ],
      "occluded": {
        "tip": true,
        "tail": false
      },
      "status": "ok",
      "method": "optical_flow_gui"
    },
    "000201": {
      "needle_tip": [
        528,
        503
      ],
      "needle_tail": [
        707,
        484
      ],
      "occluded": {
        "tip": true,
        "tail": false
      },
      "status": "ok",
      "method": "optical_flow_gui"
    },
    "000202": {
      "needle_tip": [
        529,
        503
      ],
      "needle_tail": [
        707,
        484
      ],
      "occluded": {
        "tip": true,
        "tail": false
      },
      "status": "ok",
      "method": "optical_flow_gui"
    },
    "000203": {
      "needle_tip": [
        520,
        507
      ],
      "needle_tail": [
        702,
        479
      ],
      "occluded": {
        "tip": true,
        "tail": false
      },
      "status": "ok",
      "method": "optical_flow_gui"
    },
    "000204": {
      "needle_tip": [
        507,
        515
      ],
      "needle_tail": [
        697,
        469
      ],
      "occluded": {
        "tip": true,
        "tail": false
      },
      "status": "ok",
      "method": "optical_flow_gui"
    },
    "000205": {
      "needle_tip": [
        491,
        536
      ],
      "needle_tail": [
        713,
        460
      ],
      "occluded": {
        "tip": true,
        "tail": false
      },
      "status": "ok",
      "method": "optical_flow_gui"
    },
    "000206": {
      "needle_tip": [
        489,
        543
      ],
      "needle_tail": [
        723,
        456
      ],
      "occluded": {
        "tip": true,
        "tail": false
      },
      "status": "ok",
      "method": "optical_flow_gui"
    },
    "000207": {
      "needle_tip": [
        426,
        602
      ],
      "needle_tail": [
        751,
        441
      ],
      "occluded": {
        "tip": true,
        "tail": false
      },
      "status": "ok",
      "method": "optical_flow_gui"
    },
    "000208": {
      "needle_tip": [
        455,
        587
      ],
      "needle_tail": [
        789,
        396
      ],
      "occluded": {
        "tip": true,
        "tail": false
      },
      "status": "ok",
      "method": "optical_flow_gui"
    },
    "000209": {
      "needle_tip": [
        465,
        585
      ],
      "needle_tail": [
        799,
        362
      ],
      "occluded": {
        "tip": true,
        "tail": false
      },
      "status": "ok",
      "method": "optical_flow_gui"
    },
    "000210": {
      "needle_tip": [
        467,
        582
      ],
      "needle_tail": [
        801,
        348
      ],
      "occluded": {
        "tip": true,
        "tail": false
      },
      "status": "ok",
      "method": "optical_flow_gui"
    },
    "000211": {
      "needle_tip": [
        468,
        583
      ],
      "needle_tail": [
        800,
        339
      ],
      "occluded": {
        "tip": true,
        "tail": false
      },
      "status": "ok",
      "method": "optical_flow_gui"
    },
    "000212": {
      "needle_tip": [
        472,
        585
      ],
      "needle_tail": [
        799,
        322
      ],
      "occluded": {
        "tip": true,
        "tail": false
      },
      "status": "ok",
      "method": "optical_flow_gui"
    },
    "000213": {
      "needle_tip": [
        474,
        587
      ],
      "needle_tail": [
        796,
        292
      ],
      "occluded": {
        "tip": true,
        "tail": false
      },
      "status": "ok",
      "method": "optical_flow_gui"
    },
    "000214": {
      "needle_tip": [
        783,
        474
      ],
      "needle_tail": [
        794,
        255
      ],
      "occluded": {
        "tip": false,
        "tail": false
      },
      "status": "ok",
      "method": "optical_flow_gui"
    },
    "000215": {
      "needle_tip": [
        783,
        461
      ],
      "needle_tail": [
        786,
        231
      ],
      "occluded": {
        "tip": false,
        "tail": false
      },
      "status": "ok",
      "method": "optical_flow_gui"
    },
    "000216": {
      "needle_tip": [
        785,
        452
      ],
      "needle_tail": [
        784,
        224
      ],
      "occluded": {
        "tip": false,
        "tail": false
      },
      "status": "ok",
      "method": "optical_flow_gui"
    },
    "000217": {
      "needle_tip": [
        783,
        452
      ],
      "needle_tail": [
        783,
        222
      ],
      "occluded": {
        "tip": false,
        "tail": false
      },
      "status": "ok",
      "method": "optical_flow_gui"
    },
    "000218": {
      "needle_tip": [
        784,
        451
      ],
      "needle_tail": [
        783,
        222
      ],
      "occluded": {
        "tip": false,
        "tail": false
      },
      "status": "ok",
      "method": "optical_flow_gui"
    },
    "000219": {
      "needle_tip": [
        782,
        451
      ],
      "needle_tail": [
        782,
        221
      ],
      "occluded": {
        "tip": false,
        "tail": false
      },
      "status": "ok",
      "method": "optical_flow_gui"
    },
    "000220": {
      "needle_tip": [
        762,
        428
      ],
      "needle_tail": [
        770,
        197
      ],
      "occluded": {
        "tip": false,
        "tail": false
      },
      "status": "ok",
      "method": "optical_flow_gui"
    },
    "000221": {
      "needle_tip": [
        630,
        403
      ],
      "needle_tail": [
        751,
        192
      ],
      "occluded": {
        "tip": false,
        "tail": false
      },
      "status": "ok",
      "method": "optical_flow_gui"
    },
    "000222": {
      "needle_tip": [
        594,
        429
      ],
      "needle_tail": [
        741,
        260
      ],
      "occluded": {
        "tip": false,
        "tail": false
      },
      "status": "ok",
      "method": "optical_flow_gui"
    },
    "000223": {
      "needle_tip": [
        570,
        437
      ],
      "needle_tail": [
        741,
        302
      ],
      "occluded": {
        "tip": false,
        "tail": false
      },
      "status": "ok",
      "method": "optical_flow_gui"
    },
    "000224": {
      "needle_tip": [
        567,
        467
      ],
      "needle_tail": [
        736,
        340
      ],
      "occluded": {
        "tip": false,
        "tail": false
      },
      "status": "ok",
      "method": "optical_flow_gui"
    },
    "000225": {
      "needle_tip": [
        566,
        494
      ],
      "needle_tail": [
        737,
        374
      ],
      "occluded": {
        "tip": false,
        "tail": false
      },
      "status": "ok",
      "method": "optical_flow_gui"
    },
    "000226": {
      "needle_tip": [
        572,
        506
      ],
      "needle_tail": [
        738,
        392
      ],
      "occluded": {
        "tip": false,
        "tail": false
      },
      "status": "ok",
      "method": "optical_flow_gui"
    },
    "000227": {
      "needle_tip": [
        570,
        509
      ],
      "needle_tail": [
        738,
        396
      ],
      "occluded": {
        "tip": false,
        "tail": false
      },
      "status": "ok",
      "method": "optical_flow_gui"
    },
    "000228": {
      "needle_tip": [
        567,
        516
      ],
      "needle_tail": [
        738,
        411
      ],
      "occluded": {
        "tip": false,
        "tail": false
      },
      "status": "ok",
      "method": "optical_flow_gui"
    },
    "000229": {
      "needle_tip": [
        568,
        537
      ],
      "needle_tail": [
        736,
        430
      ],
      "occluded": {
        "tip": false,
        "tail": false
      },
      "status": "ok",
      "method": "optical_flow_gui"
    },
    "000230": {
      "needle_tip": [
        565,
        542
      ],
      "needle_tail": [
        736,
        436
      ],
      "occluded": {
        "tip": false,
        "tail": false
      },
      "status": "ok",
      "method": "optical_flow_gui"
    },
    "000231": {
      "needle_tip": [
        612,
        502
      ],
      "needle_tail": [
        736,
        437
      ],
      "occluded": {
        "tip": true,
        "tail": false
      },
      "status": "ok",
      "method": "optical_flow_gui"
    },
    "000232": {
      "needle_tip": [
        612,
        502
      ],
      "needle_tail": [
        736,
        437
      ],
      "occluded": {
        "tip": true,
        "tail": false
      },
      "status": "ok",
      "method": "optical_flow_gui"
    },
    "000233": {
      "needle_tip": [
        614,
        503
      ],
      "needle_tail": [
        736,
        437
      ],
      "occluded": {
        "tip": true,
        "tail": false
      },
      "status": "ok",
      "method": "optical_flow_gui"
    },
    "000234": {
      "needle_tip": [
        617,
        502
      ],
      "needle_tail": [
        736,
        438
      ],
      "occluded": {
        "tip": true,
        "tail": false
      },
      "status": "ok",
      "method": "optical_flow_gui"
    },
    "000235": {
      "needle_tip": [
        618,
        502
      ],
      "needle_tail": [
        736,
        438
      ],
      "occluded": {
        "tip": true,
        "tail": false
      },
      "status": "ok",
      "method": "optical_flow_gui"
    },
    "000236": {
      "needle_tip": [
        618,
        503
      ],
      "needle_tail": [
        736,
        438
      ],
      "occluded": {
        "tip": true,
        "tail": false
      },
      "status": "ok",
      "method": "optical_flow_gui"
    },
    "000237": {
      "needle_tip": [
        616,
        502
      ],
      "needle_tail": [
        736,
        438
      ],
      "occluded": {
        "tip": true,
        "tail": false
      },
      "status": "ok",
      "method": "optical_flow_gui"
    },
    "000238": {
      "needle_tip": [
        614,
        502
      ],
      "needle_tail": [
        736,
        438
      ],
      "occluded": {
        "tip": true,
        "tail": false
      },
      "status": "ok",
      "method": "optical_flow_gui"
    },
    "000239": {
      "needle_tip": [
        617,
        502
      ],
      "needle_tail": [
        736,
        438
      ],
      "occluded": {
        "tip": true,
        "tail": false
      },
      "status": "ok",
      "method": "optical_flow_gui"
    },
    "000240": {
      "needle_tip": [
        613,
        502
      ],
      "needle_tail": [
        736,
        438
      ],
      "occluded": {
        "tip": true,
        "tail": false
      },
      "status": "ok",
      "method": "optical_flow_gui"
    },
    "000241": {
      "needle_tip": [
        616,
        502
      ],
      "needle_tail": [
        736,
        438
      ],
      "occluded": {
        "tip": true,
        "tail": false
      },
      "status": "ok",
      "method": "optical_flow_gui"
    },
    "000242": {
      "needle_tip": [
        616,
        502
      ],
      "needle_tail": [
        736,
        438
      ],
      "occluded": {
        "tip": true,
        "tail": false
      },
      "status": "ok",
      "method": "optical_flow_gui"
    },
    "000243": {
      "needle_tip": [
        618,
        500
      ],
      "needle_tail": [
        736,
        438
      ],
      "occluded": {
        "tip": true,
        "tail": false
      },
      "status": "ok",
      "method": "optical_flow_gui"
    },
    "000244": {
      "needle_tip": [
        621,
        498
      ],
      "needle_tail": [
        736,
        438
      ],
      "occluded": {
        "tip": true,
        "tail": false
      },
      "status": "ok",
      "method": "optical_flow_gui"
    },
    "000245": {
      "needle_tip": [
        620,
        499
      ],
      "needle_tail": [
        736,
        438
      ],
      "occluded": {
        "tip": true,
        "tail": false
      },
      "status": "ok",
      "method": "optical_flow_gui"
    },
    "000246": {
      "needle_tip": [
        622,
        500
      ],
      "needle_tail": [
        736,
        438
      ],
      "occluded": {
        "tip": true,
        "tail": false
      },
      "status": "ok",
      "method": "optical_flow_gui"
    },
    "000247": {
      "needle_tip": [
        619,
        500
      ],
      "needle_tail": [
        736,
        438
      ],
      "occluded": {
        "tip": true,
        "tail": false
      },
      "status": "ok",
      "method": "optical_flow_gui"
    },
    "000248": {
      "needle_tip": [
        622,
        499
      ],
      "needle_tail": [
        736,
        438
      ],
      "occluded": {
        "tip": true,
        "tail": false
      },
      "status": "ok",
      "method": "optical_flow_gui"
    },
    "000249": {
      "needle_tip": [
        621,
        499
      ],
      "needle_tail": [
        736,
        438
      ],
      "occluded": {
        "tip": true,
        "tail": false
      },
      "status": "ok",
      "method": "optical_flow_gui"
    },
    "000250": {
      "needle_tip": [
        625,
        498
      ],
      "needle_tail": [
        736,
        438
      ],
      "occluded": {
        "tip": true,
        "tail": false
      },
      "status": "ok",
      "method": "optical_flow_gui"
    }
  }
}
